lamzip/lamzip.py
lamzip-0.4.1.dist-info/LICENSE
lamzip-0.4.1.dist-info/METADATA
lamzip-0.4.1.dist-info/WHEEL
lamzip-0.4.1.dist-info/entry_points.txt
lamzip-0.4.1.dist-info/top_level.txt
lamzip-0.4.1.dist-info/RECORD
