Metadata-Version: 2.1
Name: lamzip
Version: 0.4.1
Summary: A simple packaging utility that creates an AWS Lambda zip for distribution
Home-page: https://github.com/seans11/lambda-zip
Author: Sean Sydow
Author-email: 
License: MIT
Keywords: aws,lambda,package,function,zip
Platform: UNKNOWN
